<?xml version='1.0'?>
<!-- Generated by LavishSettings v1 -->
<InnerSpaceSettings>
	<Set Name="Bruiser">
		<Setting Name="1,152">Jab</Setting>
		<Setting Name="1,160">Taunt</Setting>
		<Setting Name="2,120">Bruising Fist</Setting>
		<Setting Name="3,320">Ignore Bruises</Setting>
		<Setting Name="4,295">Brawler\'s Stance</Setting>
		<Setting Name="4,290">Heated Fists</Setting>
		<Setting Name="5,303">Fighting Chance</Setting>
		<Setting Name="5,151">Kick</Setting>
		<Setting Name="6,270">Intervene</Setting>
		<Setting Name="7,95">Blazing Strikes</Setting>
		<Setting Name="8,170">Impose</Setting>
		<Setting Name="9,160">Brag</Setting>
		<Setting Name="9,22">Brutality</Setting>
		<Setting Name="10,320">Ignore Wounds</Setting>
		<Setting Name="10,154">Stamp</Setting>
		<Setting Name="11,70">Burn Through</Setting>
		<Setting Name="12,25">Dodge and Strike</Setting>
		<Setting Name="13,211">Indomitable Will</Setting>
		<Setting Name="13,153">Shoulder Charge</Setting>
		<Setting Name="14,324">Feign Death</Setting>
		<Setting Name="15,152">Knuckle</Setting>
		<Setting Name="15,155">Thundering Fists</Setting>
		<Setting Name="16,295">Bouncer\'s Stance</Setting>
		<Setting Name="17,321">Bruising Strike</Setting>
		<Setting Name="17,160">Taunting Slap</Setting>
		<Setting Name="18,30">Staggering Stance</Setting>
		<Setting Name="19,151">Flying Kick</Setting>
		<Setting Name="19,150">Rapid Swings</Setting>
		<Setting Name="20,320">Ignore Pain</Setting>
		<Setting Name="20,270">Intercept</Setting>
		<Setting Name="21,290">Stance: Fiery Fists</Setting>
		<Setting Name="21,95">Whirling Blaze</Setting>
		<Setting Name="22,170">Jeer</Setting>
		<Setting Name="22,26">Roughhouse</Setting>
		<Setting Name="23,22">Intimidating Orders</Setting>
		<Setting Name="24,154">Crash</Setting>
		<Setting Name="24,322">Intimidate</Setting>
		<Setting Name="25,70">Break Through</Setting>
		<Setting Name="25,320">Rescue</Setting>
		<Setting Name="26,25">Bob and Weave</Setting>
		<Setting Name="26,156">Bruising Spirit</Setting>
		<Setting Name="27,211">Burning Will</Setting>
		<Setting Name="27,153">Fierce Punch</Setting>
		<Setting Name="28,80">Eye Gouge</Setting>
		<Setting Name="28,324">Play Dead</Setting>
		<Setting Name="29,152">Blitz</Setting>
		<Setting Name="29,155">Jolting Fists</Setting>
		<Setting Name="30,190">Haymaker</Setting>
		<Setting Name="30,323">Instill Doubt</Setting>				
		<Setting Name="30,295">Stance: Bouncer</Setting>
		<Setting Name="31,321">Grapple</Setting>
		<Setting Name="31,160">Slurred Insult</Setting>
		<Setting Name="32,30">Overtaking Blows</Setting>
		<Setting Name="32,110">Sucker Punch</Setting>
		<Setting Name="33,150">One Hundred Hand Slap</Setting>
		<Setting Name="33,151">Throat Kick</Setting>
		<Setting Name="34,320">Ignore Hurt</Setting>
		<Setting Name="34,270">Intercede</Setting>
		<Setting Name="35,95">Beatdown</Setting>
		<Setting Name="35,290">Stance: Lava Fists</Setting>
		<Setting Name="36,170">Boast</Setting>
		<Setting Name="36,26">Brawl</Setting>
		<Setting Name="37,22">Rousing Cry</Setting>
		<Setting Name="38,154">Merciless Stomp</Setting>
		<Setting Name="38,322">Strong Arm</Setting>
		<Setting Name="39,70">Burning Lunge</Setting>
		<Setting Name="40,25">Battle Fury</Setting>
		<Setting Name="40,307">Heavy Scarring</Setting>
		<Setting Name="40,156">Strapping Spirit</Setting>
		<Setting Name="41,211">Cerebral Will</Setting>
		<Setting Name="41,153">Hammer Fist</Setting>
		<Setting Name="42,80">Eye Rake</Setting>
		<Setting Name="42,324">Stop Heart</Setting>
		<Setting Name="43,152">Pummel</Setting>
		<Setting Name="43,155">Shocking Fists</Setting>
		<Setting Name="44,190">Crusher</Setting>
		<Setting Name="44,">Stance: Fire Stance</Setting>
		<Setting Name="44,295">Stance: Retaliation</Setting>
		<Setting Name="45,160">Instigate</Setting>
		<Setting Name="45,321">Meteor Punch</Setting>
		<Setting Name="46,110">Dirty Punch</Setting>
		<Setting Name="46,30">Shrug Off</Setting>
		<Setting Name="47,150">Crushing Fury</Setting>
		<Setting Name="47,151">Roundhouse</Setting>
		<Setting Name="48,320">Ignore Agony</Setting>
		<Setting Name="49,95">Bone Crusher</Setting>
		<Setting Name="49,290">Stance: Magmatic Fists</Setting>
		<Setting Name="50,170">Abuse</Setting>
		<Setting Name="50,323">Instill Panic</Setting>
		<Setting Name="50,26">Quarrel</Setting>
		<Setting Name="50,96">Savage Blows</Setting>
		<Setting Name="54,25">Battle Lust</Setting>
		<Setting Name="54,156">Deadly Spirit</Setting>
		<Setting Name="55,211">Resolute Will</Setting>
		<Setting Name="55,325">Sonic Fists</Setting>
		<Setting Name="57,155">Storming Fists</Setting>
		<Setting Name=","></Setting>
		<Setting Name=","></Setting>
	</Set>
</InnerSpaceSettings>